[
  {
    "FIELD1":"3i Group"
  },
  {
    "FIELD1":"3i Infrastructure"
  },
  {
    "FIELD1":"Aberforth Smaller Companies Trust"
  },
  {
    "FIELD1":"Aegis Group"
  },
  {
    "FIELD1":"Afren"
  },
  {
    "FIELD1":"African Barrick Gold"
  },
  {
    "FIELD1":"Alliance Trust"
  },
  {
    "FIELD1":"Amlin"
  },
  {
    "FIELD1":"Anite"
  },
  {
    "FIELD1":"Aquarius Platinum Ltd."
  },
  {
    "FIELD1":"Ashtead Group"
  },
  {
    "FIELD1":"Atkins (WS)"
  },
  {
    "FIELD1":"Aveva Group"
  },
  {
    "FIELD1":"Avocet Mining"
  },
  {
    "FIELD1":"AZ Electronic Materials SA (DI)"
  },
  {
    "FIELD1":"Balfour Beatty"
  },
  {
    "FIELD1":"Bank of Georgia Holdings"
  },
  {
    "FIELD1":"Bankers Inv Trust"
  },
  {
    "FIELD1":"Barr (A.G.)"
  },
  {
    "FIELD1":"Barratt Developments"
  },
  {
    "FIELD1":"BBA Aviation"
  },
  {
    "FIELD1":"Beazley"
  },
  {
    "FIELD1":"Bellway"
  },
  {
    "FIELD1":"Berendsen"
  },
  {
    "FIELD1":"Berkeley Group Holdings (The)"
  },
  {
    "FIELD1":"Betfair Group"
  },
  {
    "FIELD1":"BH Global Ltd. GBP Shares"
  },
  {
    "FIELD1":"BH Global Ltd. USD Shares"
  },
  {
    "FIELD1":"BH Macro Ltd. EUR Shares"
  },
  {
    "FIELD1":"BH Macro Ltd. GBP Shares"
  },
  {
    "FIELD1":"BH Macro Ltd. USD Shares"
  },
  {
    "FIELD1":"Big Yellow Group"
  },
  {
    "FIELD1":"BlackRock World Mining Trust"
  },
  {
    "FIELD1":"BlueCrest AllBlue Fund Ltd. GBP .."
  },
  {
    "FIELD1":"Bodycote"
  },
  {
    "FIELD1":"Booker Group"
  },
  {
    "FIELD1":"Bovis Homes Group"
  },
  {
    "FIELD1":"Brewin Dolphin Holdings"
  },
  {
    "FIELD1":"British Assets Trust"
  },
  {
    "FIELD1":"British Empire Securities & Gene.."
  },
  {
    "FIELD1":"Britvic"
  },
  {
    "FIELD1":"Brown (N.) Group"
  },
  {
    "FIELD1":"BTG"
  },
  {
    "FIELD1":"Bumi"
  },
  {
    "FIELD1":"Bwin.party Digital Entertainment"
  },
  {
    "FIELD1":"Cable & Wireless Communications"
  },
  {
    "FIELD1":"Cairn Energy"
  },
  {
    "FIELD1":"Caledonia Investments"
  },
  {
    "FIELD1":"Cape"
  },
  {
    "FIELD1":"Capital & Counties Properties"
  },
  {
    "FIELD1":"Carillion"
  },
  {
    "FIELD1":"Carpetright"
  },
  {
    "FIELD1":"Catlin Group Ltd."
  },
  {
    "FIELD1":"Centamin (DI)"
  },
  {
    "FIELD1":"Chemring Group"
  },
  {
    "FIELD1":"City of London Inv Trust"
  },
  {
    "FIELD1":"Close Brothers Group"
  },
  {
    "FIELD1":"Cobham"
  },
  {
    "FIELD1":"COLT Group SA"
  },
  {
    "FIELD1":"Computacenter"
  },
  {
    "FIELD1":"Cookson Group"
  },
  {
    "FIELD1":"Cranswick"
  },
  {
    "FIELD1":"CSR"
  },
  {
    "FIELD1":"Daejan Holdings"
  },
  {
    "FIELD1":"Dairy Crest Group"
  },
  {
    "FIELD1":"De La Rue"
  },
  {
    "FIELD1":"Debenhams"
  },
  {
    "FIELD1":"Dechra Pharmaceuticals"
  },
  {
    "FIELD1":"Derwent London"
  },
  {
    "FIELD1":"Devro"
  },
  {
    "FIELD1":"Dexion Absolute Ltd. GBP Shares"
  },
  {
    "FIELD1":"Dialight"
  },
  {
    "FIELD1":"Dignity"
  },
  {
    "FIELD1":"Diploma"
  },
  {
    "FIELD1":"Dixons Retail"
  },
  {
    "FIELD1":"Domino Printing Sciences"
  },
  {
    "FIELD1":"Domino's Pizza Group"
  },
  {
    "FIELD1":"Drax Group"
  },
  {
    "FIELD1":"Dunelm Group"
  },
  {
    "FIELD1":"easyJet"
  },
  {
    "FIELD1":"Edinburgh Dragon Trust"
  },
  {
    "FIELD1":"Edinburgh Inv Trust"
  },
  {
    "FIELD1":"Electra Private Equity"
  },
  {
    "FIELD1":"Electrocomponents"
  },
  {
    "FIELD1":"Elementis"
  },
  {
    "FIELD1":"EnQuest"
  },
  {
    "FIELD1":"Essar Energy"
  },
  {
    "FIELD1":"Euromoney Institutional Investor"
  },
  {
    "FIELD1":"F&C Asset Management"
  },
  {
    "FIELD1":"F&C Commercial Property Trust Ltd."
  },
  {
    "FIELD1":"Fenner"
  },
  {
    "FIELD1":"Ferrexpo"
  },
  {
    "FIELD1":"Fidelity China Special Situations"
  },
  {
    "FIELD1":"Fidelity European Values"
  },
  {
    "FIELD1":"Fidessa Group"
  },
  {
    "FIELD1":"Filtrona PLC"
  },
  {
    "FIELD1":"FirstGroup"
  },
  {
    "FIELD1":"Foreign and Colonial Inv Trust"
  },
  {
    "FIELD1":"Galliford Try"
  },
  {
    "FIELD1":"Gem Diamonds Ltd. (DI)"
  },
  {
    "FIELD1":"Genesis Emerging Markets Fund Ltd."
  },
  {
    "FIELD1":"Genus"
  },
  {
    "FIELD1":"Go-Ahead Group"
  },
  {
    "FIELD1":"Grainger"
  },
  {
    "FIELD1":"Great Portland Estates"
  },
  {
    "FIELD1":"Greene King"
  },
  {
    "FIELD1":"Greggs"
  },
  {
    "FIELD1":"Halfords Group"
  },
  {
    "FIELD1":"Halma"
  },
  {
    "FIELD1":"Hansteen Holdings"
  },
  {
    "FIELD1":"Hays"
  },
  {
    "FIELD1":"Henderson Group"
  },
  {
    "FIELD1":"Herald Inv Trust"
  },
  {
    "FIELD1":"Heritage Oil"
  },
  {
    "FIELD1":"HICL Infrastructure Company Ltd"
  },
  {
    "FIELD1":"Hikma Pharmaceuticals"
  },
  {
    "FIELD1":"Hiscox Ltd."
  },
  {
    "FIELD1":"Hochschild Mining"
  },
  {
    "FIELD1":"Home Retail Group"
  },
  {
    "FIELD1":"Homeserve"
  },
  {
    "FIELD1":"Howden Joinery Group"
  },
  {
    "FIELD1":"Hunting"
  },
  {
    "FIELD1":"IG Group Holdings"
  },
  {
    "FIELD1":"Imagination Technologies Group"
  },
  {
    "FIELD1":"Inchcape"
  },
  {
    "FIELD1":"Informa"
  },
  {
    "FIELD1":"Inmarsat"
  },
  {
    "FIELD1":"Intermediate Capital Group"
  },
  {
    "FIELD1":"International Personal Finance"
  },
  {
    "FIELD1":"International Public Partnership.."
  },
  {
    "FIELD1":"Interserve"
  },
  {
    "FIELD1":"Invensys"
  },
  {
    "FIELD1":"Investec"
  },
  {
    "FIELD1":"IP Group"
  },
  {
    "FIELD1":"ITE Group"
  },
  {
    "FIELD1":"Jardine Lloyd Thompson Group"
  },
  {
    "FIELD1":"JD Sports Fashion"
  },
  {
    "FIELD1":"John Laing Infrastructure Fund Ltd"
  },
  {
    "FIELD1":"JPMorgan American Inv Trust"
  },
  {
    "FIELD1":"JPMorgan Asian Inv Trust"
  },
  {
    "FIELD1":"JPMorgan Emerging Markets Inv Tr.."
  },
  {
    "FIELD1":"JPMorgan Indian Inv Trust"
  },
  {
    "FIELD1":"Jupiter Fund Management"
  },
  {
    "FIELD1":"KCOM Group"
  },
  {
    "FIELD1":"Kenmare Resources"
  },
  {
    "FIELD1":"Kentz Corporation Ltd."
  },
  {
    "FIELD1":"Kier Group"
  },
  {
    "FIELD1":"Ladbrokes"
  },
  {
    "FIELD1":"Laird"
  },
  {
    "FIELD1":"Lancashire Holdings"
  },
  {
    "FIELD1":"Law Debenture Corp."
  },
  {
    "FIELD1":"Logica"
  },
  {
    "FIELD1":"London & Stamford Property"
  },
  {
    "FIELD1":"London Stock Exchange Group"
  },
  {
    "FIELD1":"Lonmin"
  },
  {
    "FIELD1":"Man Group"
  },
  {
    "FIELD1":"Marston's"
  },
  {
    "FIELD1":"Melrose"
  },
  {
    "FIELD1":"Menzies(John)"
  },
  {
    "FIELD1":"Mercantile Investment Trust (The)"
  },
  {
    "FIELD1":"Merchants Trust"
  },
  {
    "FIELD1":"Michael Page International"
  },
  {
    "FIELD1":"Micro Focus International"
  },
  {
    "FIELD1":"Millennium & Copthorne Hotels"
  },
  {
    "FIELD1":"Mitchells & Butlers"
  },
  {
    "FIELD1":"Mitie Group"
  },
  {
    "FIELD1":"Mondi"
  },
  {
    "FIELD1":"Moneysupermarket.com Group"
  },
  {
    "FIELD1":"Monks Inv Trust"
  },
  {
    "FIELD1":"Morgan Crucible Co"
  },
  {
    "FIELD1":"Murray Income Trust"
  },
  {
    "FIELD1":"Murray International Trust"
  },
  {
    "FIELD1":"National Express Group"
  },
  {
    "FIELD1":"NB Global Floating Rate Income F.."
  },
  {
    "FIELD1":"New World Resources A Shares"
  },
  {
    "FIELD1":"NMC Health"
  },
  {
    "FIELD1":"Ocado Group"
  },
  {
    "FIELD1":"Ophir Energy"
  },
  {
    "FIELD1":"Oxford Instruments"
  },
  {
    "FIELD1":"Paragon Group Of Companies"
  },
  {
    "FIELD1":"PayPoint"
  },
  {
    "FIELD1":"Perform Group"
  },
  {
    "FIELD1":"Perpetual Income & Growth Inv Tr.."
  },
  {
    "FIELD1":"Persimmon"
  },
  {
    "FIELD1":"Personal Assets Trust"
  },
  {
    "FIELD1":"Petra Diamonds Ltd.(DI)"
  },
  {
    "FIELD1":"Petropavlovsk"
  },
  {
    "FIELD1":"Phoenix Group Holdings (DI)"
  },
  {
    "FIELD1":"Polar Capital Technology Trust"
  },
  {
    "FIELD1":"Premier Farnell"
  },
  {
    "FIELD1":"Premier Oil"
  },
  {
    "FIELD1":"Provident Financial"
  },
  {
    "FIELD1":"PZ Cussons"
  },
  {
    "FIELD1":"QinetiQ Group"
  },
  {
    "FIELD1":"Rank Group"
  },
  {
    "FIELD1":"Rathbone Brothers"
  },
  {
    "FIELD1":"Raven Russia Ltd"
  },
  {
    "FIELD1":"Redrow"
  },
  {
    "FIELD1":"Regus"
  },
  {
    "FIELD1":"Renishaw"
  },
  {
    "FIELD1":"Rentokil Initial"
  },
  {
    "FIELD1":"Restaurant Group"
  },
  {
    "FIELD1":"Rightmove"
  },
  {
    "FIELD1":"RIT Capital Partners"
  },
  {
    "FIELD1":"Rotork"
  },
  {
    "FIELD1":"RPC Group"
  },
  {
    "FIELD1":"RPS Group"
  },
  {
    "FIELD1":"Ruspetro"
  },
  {
    "FIELD1":"Salamander Energy"
  },
  {
    "FIELD1":"Savills"
  },
  {
    "FIELD1":"Scottish Inv Trust"
  },
  {
    "FIELD1":"Scottish Mortgage Inv Trust"
  },
  {
    "FIELD1":"SDL"
  },
  {
    "FIELD1":"SEGRO"
  },
  {
    "FIELD1":"Senior"
  },
  {
    "FIELD1":"Shaftesbury"
  },
  {
    "FIELD1":"Shanks Group"
  },
  {
    "FIELD1":"SIG"
  },
  {
    "FIELD1":"Smith (DS)"
  },
  {
    "FIELD1":"Soco International"
  },
  {
    "FIELD1":"Spectris"
  },
  {
    "FIELD1":"Spirax-Sarco Engineering"
  },
  {
    "FIELD1":"Spirent Communications"
  },
  {
    "FIELD1":"Sports Direct International"
  },
  {
    "FIELD1":"St James's Place"
  },
  {
    "FIELD1":"Stagecoach Group"
  },
  {
    "FIELD1":"Stobart Group Ltd."
  },
  {
    "FIELD1":"SVG Capital"
  },
  {
    "FIELD1":"Synergy Health"
  },
  {
    "FIELD1":"TalkTalk Telecom Group"
  },
  {
    "FIELD1":"Talvivaara Mining Company"
  },
  {
    "FIELD1":"Taylor Wimpey"
  },
  {
    "FIELD1":"Ted Baker"
  },
  {
    "FIELD1":"Telecity Group"
  },
  {
    "FIELD1":"Telecom Plus"
  },
  {
    "FIELD1":"Temple Bar Inv Trust"
  },
  {
    "FIELD1":"Templeton Emerging Markets Inv T.."
  },
  {
    "FIELD1":"TR Property Inv Trust"
  },
  {
    "FIELD1":"TR Property Inv Trust Sigma Shares"
  },
  {
    "FIELD1":"Travis Perkins"
  },
  {
    "FIELD1":"TUI Travel"
  },
  {
    "FIELD1":"Tullett Prebon"
  },
  {
    "FIELD1":"UBM"
  },
  {
    "FIELD1":"UK Commercial Property Trust"
  },
  {
    "FIELD1":"Ultra Electronics Holdings"
  },
  {
    "FIELD1":"Utilico Emerging Markets Ltd (DI)"
  },
  {
    "FIELD1":"Victrex"
  },
  {
    "FIELD1":"Wetherspoon (J.D.)"
  },
  {
    "FIELD1":"WH Smith"
  },
  {
    "FIELD1":"William Hill"
  },
  {
    "FIELD1":"Witan Inv Trust"
  },
  {
    "FIELD1":"Wood Group (John)"
  },
  {
    "FIELD1":"Worldwide Healthcare Trust"
  },
  {
    "FIELD1":"Yule Catto & Co"
  }
]
